setup.py
vecnet/__init__.py
vecnet.egg-info/PKG-INFO
vecnet.egg-info/SOURCES.txt
vecnet.egg-info/dependency_links.txt
vecnet.egg-info/namespace_packages.txt
vecnet.egg-info/requires.txt
vecnet.egg-info/top_level.txt