Metadata-Version: 1.1
Name: vecnet
Version: 1.0.0
Summary: Virtual package for installing all packages in vecnet namespace
Home-page: https://github.com/vecnet/vecnet.openmalaria
Author: University of Notre Dame
Author-email: dev@vecnet.org
License: MPL 2.0
Keywords: openamalaria malaria vecnet
Platform: UNKNOWN
Classifier: Development Status :: 3 - Alpha
Classifier: License :: OSI Approved :: Mozilla Public License 2.0 (MPL 2.0)
Classifier: Intended Audience :: Developers
Classifier: Operating System :: OS Independent
Classifier: Programming Language :: Python
Classifier: Programming Language :: Python :: 2
Classifier: Programming Language :: Python :: 2.7
Classifier: Topic :: Software Development :: Libraries :: Python Modules
